{"nodes": [{"id": "dropdownmenu_dropdownmenu", "label": "DropdownMenu", "file_type": "code", "source_file": "docs-components-dropdown-menu.md", "source_location": null, "source_url": "https://www.radix-ui.com/docs/primitives/components/dropdown-menu", "captured_at": null, "author": null, "contributor": null}, {"id": "dropdownmenu_dropdownmenucontent", "label": "DropdownMenuContent", "file_type": "code", "source_file": "docs-components-dropdown-menu.md", "source_location": null, "source_url": null, "captured_at": null, "author": null, "contributor": null}, {"id": "dropdownmenu_dropdownmenugroup", "label": "DropdownMenuGroup", "file_type": "code", "source_file": "docs-components-dropdown-menu.md", "source_location": null, "source_url": null, "captured_at": null, "author": null, "contributor": null}, {"id": "dropdownmenu_dropdownmenuitem", "label": "DropdownMenuItem", "file_type": "code", "source_file": "docs-components-dropdown-menu.md", "source_location": null, "source_url": null, "captured_at": null, "author": null, "contributor": null}, {"id": "dropdownmenu_dropdownmenulabel", "label": "DropdownMenuLabel", "file_type": "code", "source_file": "docs-components-dropdown-menu.md", "source_location": null, "source_url": null, "captured_at": null, "author": null, "contributor": null}, {"id": "dropdownmenu_dropdownmenuportal", "label": "DropdownMenuPortal", "file_type": "code", "source_file": "docs-components-dropdown-menu.md", "source_location": null, "source_url": null, "captured_at": null, "author": null, "contributor": null}, {"id": "dropdownmenu_dropdownmenuseparator", "label": "DropdownMenuSeparator", "file_type": "code", "source_file": "docs-components-dropdown-menu.md", "source_location": null, "source_url": null, "captured_at": null, "author": null, "contributor": null}, {"id": "dropdownmenu_dropdownmenushortcut", "label": "DropdownMenuShortcut", "file_type": "code", "source_file": "docs-components-dropdown-menu.md", "source_location": null, "source_url": null, "captured_at": null, "author": null, "contributor": null}, {"id": "dropdownmenu_dropdownmenusub", "label": "DropdownMenuSub", "file_type": "code", "source_file": "docs-components-dropdown-menu.md", "source_location": null, "source_url": null, "captured_at": null, "author": null, "contributor": null}, {"id": "dropdownmenu_dropdownmenusubcontent", "label": "DropdownMenuSubContent", "file_type": "code", "source_file": "docs-components-dropdown-menu.md", "source_location": null, "source_url": null, "captured_at": null, "author": null, "contributor": null}, {"id": "dropdownmenu_dropdownmenusubtrigger", "label": "DropdownMenuSubTrigger", "file_type": "code", "source_file": "docs-components-dropdown-menu.md", "source_location": null, "source_url": null, "captured_at": null, "author": null, "contributor": null}, {"id": "dropdownmenu_dropdownmenutrigger", "label": "DropdownMenuTrigger", "file_type": "code", "source_file": "docs-components-dropdown-menu.md", "source_location": null, "source_url": null, "captured_at": null, "author": null, "contributor": null}, {"id": "dropdownmenu_dropdownmenucheckboxitem", "label": "DropdownMenuCheckboxItem", "file_type": "code", "source_file": "docs-components-dropdown-menu.md", "source_location": null, "source_url": null, "captured_at": null, "author": null, "contributor": null}, {"id": "dropdownmenu_dropdownmenuradiogroup", "label": "DropdownMenuRadioGroup", "file_type": "code", "source_file": "docs-components-dropdown-menu.md", "source_location": null, "source_url": null, "captured_at": null, "author": null, "contributor": null}, {"id": "dropdownmenu_dropdownmenuradioitem", "label": "DropdownMenuRadioItem", "file_type": "code", "source_file": "docs-components-dropdown-menu.md", "source_location": null, "source_url": null, "captured_at": null, "author": null, "contributor": null}, {"id": "ui_avatar", "label": "Avatar", "file_type": "code", "source_file": "docs-components-dropdown-menu.md", "source_location": null, "source_url": null, "captured_at": null, "author": null, "contributor": null}, {"id": "ui_avatarfallback", "label": "AvatarFallback", "file_type": "code", "source_file": "docs-components-dropdown-menu.md", "source_location": null, "source_url": null, "captured_at": null, "author": null, "contributor": null}, {"id": "ui_avatarimage", "label": "AvatarImage", "file_type": "code", "source_file": "docs-components-dropdown-menu.md", "source_location": null, "source_url": null, "captured_at": null, "author": null, "contributor": null}], "edges": [{"source": "dropdownmenu_dropdownmenu", "target": "radix_ui", "relation": "implements", "confidence": "EXTRACTED", "confidence_score": 1.0, "source_file": "docs-components-dropdown-menu.md", "source_location": null, "weight": 1.0}, {"source": "dropdownmenu_dropdownmenutrigger", "target": "ui_button", "relation": "calls", "confidence": "EXTRACTED", "confidence_score": 1.0, "source_file": "docs-components-dropdown-menu.md", "source_location": null, "weight": 1.0}, {"source": "dropdownmenu_dropdownmenuavatar", "target": "ui_avatar", "relation": "calls", "confidence": "EXTRACTED", "confidence_score": 1.0, "source_file": "docs-components-dropdown-menu.md", "source_location": null, "weight": 1.0}, {"source": "dropdownmenu_dropdownmenuavatar", "target": "ui_avatarimage", "relation": "calls", "confidence": "EXTRACTED", "confidence_score": 1.0, "source_file": "docs-components-dropdown-menu.md", "source_location": null, "weight": 1.0}, {"source": "dropdownmenu_dropdownmenuavatar", "target": "ui_avatarfallback", "relation": "calls", "confidence": "EXTRACTED", "confidence_score": 1.0, "source_file": "docs-components-dropdown-menu.md", "source_location": null, "weight": 1.0}], "hyperedges": []}